clarityai/__init__.py
clarityai/attention_maps.py
clarityai/saliency_maps.py
ClarityAI-1.0.0.dist-info/LICENSE
ClarityAI-1.0.0.dist-info/METADATA
ClarityAI-1.0.0.dist-info/WHEEL
ClarityAI-1.0.0.dist-info/top_level.txt
ClarityAI-1.0.0.dist-info/RECORD
